Metadata-Version: 1.1
Name: ahttptemplate
Version: 0.0.3
Summary: AioHTTP Template PackageREST API Boilerplate
Home-page: https://github.com/mpecarina/ahttptemplate.git
Author: mpecarina
Author-email: mattp@hbci.com
License: Apache 2.0
Keywords: aiohttp rest api template
Platform: UNKNOWN
Classifier: Programming Language :: Python :: 3.8
Classifier: Topic :: Software Development :: Libraries
Classifier: License :: OSI Approved :: Apache Software License
